README.rst
pakiti-client
setup.py
svmon
svmon_client/__init__.py
svmon_client/chain_TERENA_SSL_CA_3.pem
svmon_client/config.json
svmon_client/json_operations.py
svmon_client/operating_system_parser.py
svmon_client/report.py
svmon_client/services.py
svmon_client_pilot.egg-info/PKG-INFO
svmon_client_pilot.egg-info/SOURCES.txt
svmon_client_pilot.egg-info/dependency_links.txt
svmon_client_pilot.egg-info/top_level.txt