Metadata-Version: 1.2
Name: svmon-client-pilot
Version: 1.1.0
Summary: This is a python implementation of SVMON client
Home-page: https://gitlab.eudat.eu/jie.yuan/pysvmon
Author: Jie Yuan
Author-email: jie.yuan@kit.edu
Maintainer: Jie Yuan
Maintainer-email: jie.yuan@kit.edu
License: MIT License
Platform: all
Classifier: Development Status :: 4 - Beta
Classifier: Operating System :: OS Independent
Classifier: Intended Audience :: Developers
Classifier: License :: OSI Approved :: MIT License
Classifier: Programming Language :: Python
Classifier: Programming Language :: Python :: Implementation
Classifier: Programming Language :: Python :: 2.7
Classifier: Topic :: Software Development :: Libraries
